llama_index/llms/bedrock_converse/__init__.py
llama_index/llms/bedrock_converse/base.py
llama_index/llms/bedrock_converse/utils.py
basejump_llama_index_llms_bedrock_converse-0.5.0.post1.dist-info/METADATA
basejump_llama_index_llms_bedrock_converse-0.5.0.post1.dist-info/WHEEL
basejump_llama_index_llms_bedrock_converse-0.5.0.post1.dist-info/licenses/LICENSE
basejump_llama_index_llms_bedrock_converse-0.5.0.post1.dist-info/RECORD
