Metadata-Version: 2.4
Name: basejump-llama-index-llms-bedrock-converse
Version: 0.5.0.post1
Summary: llama-index llms bedrock converse integration
Author-email: Your Name <you@example.com>
License-Expression: MIT
License-File: LICENSE
Requires-Python: <4.0,>=3.9
Requires-Dist: aioboto3<14,>=13.1.1
Requires-Dist: basejump-llama-index-core<0.13,>=0.12.0
Requires-Dist: boto3<2,>=1.34.122
